{
  "intro": "Welcome",
  "heroPhoto": {
    "src": "../../images/auto-shop-front.png",
    "alt": "Our Auto Body Shop"
  },
  "image": {
    "src": "../../images/auto-repair.png",
    "alt": "Auto Repair Icon"
  },
  "title": "We're Your Trusted Auto Body Experts",
  "subtitle": {
    "prefix": "We provide top-notch ",
    "highlight": "auto repair services",
    "suffix": " tailored to your needs."
  },
  "description": "With years of experience and a team of certified professionals, we offer a wide range of services including collision repair, car painting, and dent removal. We use cutting-edge technology and high-quality materials to ensure your car looks as good as new."
}
